{"players":[{"playerID":"D.Houston-5","number":"5","name":"D.Houston","goals":"3","behinds":"0","kicks":"16","handballs":"6","marks":"8","tackles":"10","hitouts":"0","tog":"86","fantasy":"136","fantasyAvg":"90.90","team":0,"teamName":"Port Adelaide","url":null,"teamScore":"11.14","teamScoreTotal":80,"time":"Q4 34:46","sub":0,"breakeven":"105","price":"821,000","position":"DEF","benched":0,"injured":0,"subbedout":0,"tagged":0,"tagger":0,"freesfor":"0","freesagainst":"2","round":"10","date":0,"trimmedLink":2951},{"playerID":"Z.Butters-9","number":"9","name":"Z.Butters","goals":"0","behinds":"0","kicks":"16","handballs":"16","marks":"5","tackles":"6","hitouts":"0","tog":"84","fantasy":"112","fantasyAvg":"107.70","team":0,"teamName":"Port Adelaide","url":null,"teamScore":"11.14","teamScoreTotal":80,"time":"Q4 34:46","sub":0,"breakeven":"101","price":"938,000","position":"MID","benched":0,"injured":0,"subbedout":0,"tagged":0,"tagger":0,"freesfor":"2","freesagainst":"3","round":"10","date":0,"trimmedLink":2951},{"playerID":"J.Horne-Francis-18","number":"18","name":"J.Horne-Francis","goals":"2","behinds":"1","kicks":"21","handballs":"6","marks":"2","tackles":"4","hitouts":"0","tog":"86","fantasy":"112","fantasyAvg":"86.70","team":0,"teamName":"Port Adelaide","url":null,"teamScore":"11.14","teamScoreTotal":80,"time":"Q4 34:46","sub":0,"breakeven":"77","price":"711,000","position":"MID","benched":0,"injured":0,"subbedout":0,"tagged":1,"tagger":0,"freesfor":"5","freesagainst":"1","round":"10","date":0,"trimmedLink":2951},{"playerID":"T.Boak-10","number":"10","name":"T.Boak","goals":"0","behinds":"1","kicks":"16","handballs":"10","marks":"7","tackles":"5","hitouts":"0","tog":"83","fantasy":"107","fantasyAvg":"67.70","team":0,"teamName":"Port Adelaide","url":null,"teamScore":"11.14","teamScoreTotal":80,"time":"Q4 34:46","sub":0,"breakeven":"48","price":"572,000","position":"MID/FWD","benched":0,"injured":0,"subbedout":0,"tagged":0,"tagger":0,"freesfor":"0","freesagainst":"1","round":"10","date":0,"trimmedLink":2951},{"playerID":"J.Burgoyne-7","number":"7","name":"J.Burgoyne","goals":"0","behinds":"0","kicks":"13","handballs":"10","marks":"4","tackles":"7","hitouts":"0","tog":"81","fantasy":"100","fantasyAvg":"67.30","team":0,"teamName":"Port Adelaide","url":null,"teamScore":"11.14","teamScoreTotal":80,"time":"Q4 34:46","sub":0,"breakeven":"44","price":"590,000","position":"DEF/MID","benched":0,"injured":0,"subbedout":0,"tagged":0,"tagger":0,"freesfor":"1","freesagainst":"0","round":"10","date":0,"trimmedLink":2951},{"playerID":"K.Farrell-6","number":"6","name":"K.Farrell","goals":"0","behinds":"0","kicks":"18","handballs":"8","marks":"3","tackles":"3","hitouts":"0","tog":"84","fantasy":"93","fantasyAvg":"77.20","team":0,"teamName":"Port Adelaide","url":null,"teamScore":"11.14","teamScoreTotal":80,"time":"Q4 34:46","sub":0,"breakeven":"84","price":"661,000","position":"DEF","benched":0,"injured":0,"subbedout":0,"tagged":0,"tagger":0,"freesfor":"2","freesagainst":"0","round":"10","date":0,"trimmedLink":2951},{"playerID":"W.Drew-28","number":"28","name":"W.Drew","goals":"0","behinds":"0","kicks":"7","handballs":"11","marks":"0","tackles":"10","hitouts":"0","tog":"75","fantasy":"77","fantasyAvg":"88.10","team":0,"teamName":"Port Adelaide","url":null,"teamScore":"11.14","teamScoreTotal":80,"time":"Q4 34:46","sub":0,"breakeven":"84","price":"736,000","position":"MID","benched":0,"injured":0,"subbedout":0,"tagged":0,"tagger":0,"freesfor":"0","freesagainst":"2","round":"10","date":0,"trimmedLink":2951},{"playerID":"W.Rioli-15","number":"15","name":"W.Rioli","goals":"3","behinds":"1","kicks":"10","handballs":"4","marks":"1","tackles":"4","hitouts":"0","tog":"93","fantasy":"72","fantasyAvg":"53.80","team":0,"teamName":"Port Adelaide","url":null,"teamScore":"11.14","teamScoreTotal":80,"time":"Q4 34:46","sub":0,"breakeven":"18","price":"470,000","position":"FWD","benched":0,"injured":0,"subbedout":0,"tagged":0,"tagger":0,"freesfor":"2","freesagainst":"2","round":"10","date":0,"trimmedLink":2951},{"playerID":"T.Marshall-4","number":"4","name":"T.Marshall","goals":"1","behinds":"1","kicks":"10","handballs":"3","marks":"7","tackles":"1","hitouts":"0","tog":"79","fantasy":"68","fantasyAvg":"57.20","team":0,"teamName":"Port Adelaide","url":null,"teamScore":"11.14","teamScoreTotal":80,"time":"Q4 34:46","sub":0,"breakeven":"74","price":"467,000","position":"FWD","benched":0,"injured":0,"subbedout":0,"tagged":0,"tagger":0,"freesfor":"0","freesagainst":"0","round":"10","date":0,"trimmedLink":2951},{"playerID":"A.Aliir-21","number":"21","name":"A.Aliir","goals":"0","behinds":"0","kicks":"13","handballs":"4","marks":"7","tackles":"1","hitouts":"0","tog":"99","fantasy":"63","fantasyAvg":"52.10","team":0,"teamName":"Port Adelaide","url":null,"teamScore":"11.14","teamScoreTotal":80,"time":"Q4 34:46","sub":0,"breakeven":"73","price":"450,000","position":"DEF","benched":0,"injured":0,"subbedout":0,"tagged":0,"tagger":0,"freesfor":"0","freesagainst":"3","round":"10","date":0,"trimmedLink":2951},{"playerID":"J.Mead-44","number":"44","name":"J.Mead","goals":"0","behinds":"0","kicks":"8","handballs":"10","marks":"0","tackles":"4","hitouts":"0","tog":"77","fantasy":"61","fantasyAvg":"52.20","team":0,"teamName":"Port Adelaide","url":null,"teamScore":"11.14","teamScoreTotal":80,"time":"Q4 34:46","sub":0,"breakeven":"38","price":"410,000","position":"MID/FWD","benched":0,"injured":0,"subbedout":0,"tagged":0,"tagger":0,"freesfor":"1","freesagainst":"0","round":"10","date":0,"trimmedLink":2951},{"playerID":"D.Visentini-38","number":"38","name":"D.Visentini","goals":"0","behinds":"0","kicks":"3","handballs":"5","marks":"1","tackles":"3","hitouts":"29","tog":"86","fantasy":"60","fantasyAvg":"71.00","team":0,"teamName":"Port Adelaide","url":null,"teamScore":"11.14","teamScoreTotal":80,"time":"Q4 34:46","sub":0,"breakeven":"9","price":"310,000","position":"RUC","benched":0,"injured":0,"subbedout":0,"tagged":0,"tagger":0,"freesfor":"0","freesagainst":"1","round":"10","date":0,"trimmedLink":2951},{"playerID":"D.Byrne-Jones-33","number":"33","name":"D.Byrne-Jones","goals":"2","behinds":"0","kicks":"9","handballs":"4","marks":"0","tackles":"3","hitouts":"0","tog":"79","fantasy":"60","fantasyAvg":"57.20","team":0,"teamName":"Port Adelaide","url":null,"teamScore":"11.14","teamScoreTotal":80,"time":"Q4 34:46","sub":0,"breakeven":"61","price":"501,000","position":"FWD","benched":0,"injured":0,"subbedout":0,"tagged":0,"tagger":0,"freesfor":"1","freesagainst":"0","round":"10","date":0,"trimmedLink":2951},{"playerID":"M.Bergman-14","number":"14","name":"M.Bergman","goals":"0","behinds":"0","kicks":"5","handballs":"4","marks":"1","tackles":"8","hitouts":"0","tog":"88","fantasy":"58","fantasyAvg":"79.30","team":0,"teamName":"Port Adelaide","url":null,"teamScore":"11.14","teamScoreTotal":80,"time":"Q4 34:46","sub":0,"breakeven":"84","price":"689,000","position":"DEF/MID","benched":0,"injured":0,"subbedout":0,"tagged":0,"tagger":0,"freesfor":"0","freesagainst":"0","round":"10","date":0,"trimmedLink":2951},{"playerID":"C.Dixon-22","number":"22","name":"C.Dixon","goals":"0","behinds":"1","kicks":"7","handballs":"4","marks":"2","tackles":"3","hitouts":"9","tog":"74","fantasy":"58","fantasyAvg":"63.30","team":0,"teamName":"Port Adelaide","url":null,"teamScore":"11.14","teamScoreTotal":80,"time":"Q4 34:46","sub":0,"breakeven":"76","price":"567,000","position":"FWD","benched":0,"injured":0,"subbedout":0,"tagged":0,"tagger":0,"freesfor":"1","freesagainst":"0","round":"10","date":0,"trimmedLink":2951},{"playerID":"R.Burton-3","number":"3","name":"R.Burton","goals":"0","behinds":"0","kicks":"5","handballs":"4","marks":"4","tackles":"6","hitouts":"0","tog":"78","fantasy":"57","fantasyAvg":"73.40","team":0,"teamName":"Port Adelaide","url":null,"teamScore":"11.14","teamScoreTotal":80,"time":"Q4 34:46","sub":0,"breakeven":"67","price":"620,000","position":"DEF","benched":0,"injured":0,"subbedout":0,"tagged":0,"tagger":0,"freesfor":"1","freesagainst":"1","round":"10","date":0,"trimmedLink":2951},{"playerID":"E.Ratugolea-27","number":"27","name":"E.Ratugolea","goals":"0","behinds":"0","kicks":"6","handballs":"3","marks":"5","tackles":"4","hitouts":"0","tog":"84","fantasy":"53","fantasyAvg":"49.20","team":0,"teamName":"Port Adelaide","url":null,"teamScore":"11.14","teamScoreTotal":80,"time":"Q4 34:46","sub":0,"breakeven":"60","price":"431,000","position":"DEF","benched":0,"injured":0,"subbedout":0,"tagged":0,"tagger":0,"freesfor":"1","freesagainst":"1","round":"10","date":0,"trimmedLink":2951},{"playerID":"J.McEntee-41","number":"41","name":"J.McEntee","goals":"0","behinds":"0","kicks":"4","handballs":"3","marks":"2","tackles":"4","hitouts":"0","tog":"79","fantasy":"40","fantasyAvg":"28.00","team":0,"teamName":"Port Adelaide","url":null,"teamScore":"11.14","teamScoreTotal":80,"time":"Q4 34:46","sub":0,"breakeven":"42","price":"269,000","position":"FWD","benched":0,"injured":0,"subbedout":0,"tagged":0,"tagger":0,"freesfor":"0","freesagainst":"0","round":"10","date":0,"trimmedLink":2951},{"playerID":"J.Sinn-8","number":"8","name":"J.Sinn","goals":"0","behinds":"0","kicks":"9","handballs":"5","marks":"2","tackles":"0","hitouts":"0","tog":"75","fantasy":"40","fantasyAvg":"56.00","team":0,"teamName":"Port Adelaide","url":null,"teamScore":"11.14","teamScoreTotal":80,"time":"Q4 34:46","sub":0,"breakeven":"13","price":"275,000","position":"MID","benched":0,"injured":0,"subbedout":0,"tagged":0,"tagger":0,"freesfor":"0","freesagainst":"1","round":"10","date":0,"trimmedLink":2951},{"playerID":"J.Finlayson-11","number":"11","name":"J.Finlayson","goals":"0","behinds":"3","kicks":"5","handballs":"4","marks":"0","tackles":"3","hitouts":"0","tog":"68","fantasy":"35","fantasyAvg":"71.80","team":0,"teamName":"Port Adelaide","url":null,"teamScore":"11.14","teamScoreTotal":80,"time":"Q4 34:46","sub":0,"breakeven":"78","price":"639,000","position":"FWD","benched":0,"injured":0,"subbedout":0,"tagged":0,"tagger":0,"freesfor":"0","freesagainst":"1","round":"10","date":0,"trimmedLink":2951},{"playerID":"O.Wines-16","number":"16","name":"O.Wines","goals":"0","behinds":"0","kicks":"1","handballs":"6","marks":"1","tackles":"3","hitouts":"0","tog":"22","fantasy":"30","fantasyAvg":"95.80","team":0,"teamName":"Port Adelaide","url":null,"teamScore":"11.14","teamScoreTotal":80,"time":"Q4 34:46","sub":0,"breakeven":"61","price":"822,000","position":"MID","benched":0,"injured":0,"subbedout":1,"tagged":0,"tagger":0,"freesfor":"0","freesagainst":"0","round":"10","date":0,"trimmedLink":2951},{"playerID":"B.Zerk-Thatcher-25","number":"25","name":"B.Zerk-Thatcher","goals":"0","behinds":"0","kicks":"2","handballs":"3","marks":"0","tackles":"3","hitouts":"0","tog":"67","fantasy":"25","fantasyAvg":"50.00","team":0,"teamName":"Port Adelaide","url":null,"teamScore":"11.14","teamScoreTotal":80,"time":"Q4 34:46","sub":1,"breakeven":"57","price":"434,000","position":"DEF","benched":0,"injured":0,"subbedout":0,"tagged":0,"tagger":0,"freesfor":"1","freesagainst":"0","round":"10","date":0,"trimmedLink":2951},{"playerID":"M.Georgiades-19","number":"19","name":"M.Georgiades","goals":"0","behinds":"0","kicks":"3","handballs":"1","marks":"0","tackles":"1","hitouts":"0","tog":"73","fantasy":"12","fantasyAvg":"58.20","team":0,"teamName":"Port Adelaide","url":null,"teamScore":"11.14","teamScoreTotal":80,"time":"Q4 34:46","sub":0,"breakeven":"72","price":"477,000","position":"FWD","benched":0,"injured":0,"subbedout":0,"tagged":0,"tagger":0,"freesfor":"0","freesagainst":"1","round":"10","date":0,"trimmedLink":2951},{"playerID":"B.Hardwick-15","number":"15","name":"B.Hardwick","goals":"5","behinds":"0","kicks":"18","handballs":"5","marks":"6","tackles":"4","hitouts":"0","tog":"87","fantasy":"132","fantasyAvg":"61.00","team":1,"teamName":"Hawthorn","url":null,"teamScore":"12.7","teamScoreTotal":79,"time":"Q4 34:46","sub":0,"breakeven":"48","price":"539,000","position":"DEF/FWD","benched":0,"injured":0,"subbedout":0,"tagged":0,"tagger":0,"freesfor":"4","freesagainst":"0","round":"10","date":0,"trimmedLink":2951},{"playerID":"W.Day-12","number":"12","name":"W.Day","goals":"1","behinds":"0","kicks":"18","handballs":"9","marks":"4","tackles":"5","hitouts":"0","tog":"84","fantasy":"109","fantasyAvg":"63.30","team":1,"teamName":"Hawthorn","url":null,"teamScore":"12.7","teamScoreTotal":79,"time":"Q4 34:46","sub":0,"breakeven":"117","price":"728,000","position":"MID","benched":0,"injured":0,"subbedout":0,"tagged":0,"tagger":0,"freesfor":"2","freesagainst":"1","round":"10","date":0,"trimmedLink":2951},{"playerID":"L.Meek-17","number":"17","name":"L.Meek","goals":"0","behinds":"0","kicks":"6","handballs":"12","marks":"1","tackles":"4","hitouts":"45","tog":"85","fantasy":"108","fantasyAvg":"88.90","team":1,"teamName":"Hawthorn","url":null,"teamScore":"12.7","teamScoreTotal":79,"time":"Q4 34:46","sub":0,"breakeven":"34","price":"710,000","position":"RUC","benched":0,"injured":0,"subbedout":0,"tagged":0,"tagger":0,"freesfor":"2","freesagainst":"0","round":"10","date":0,"trimmedLink":2951},{"playerID":"K.Amon-10","number":"10","name":"K.Amon","goals":"0","behinds":"0","kicks":"23","handballs":"3","marks":"5","tackles":"2","hitouts":"0","tog":"88","fantasy":"96","fantasyAvg":"87.70","team":1,"teamName":"Hawthorn","url":null,"teamScore":"12.7","teamScoreTotal":79,"time":"Q4 34:46","sub":0,"breakeven":"90","price":"765,000","position":"MID/DEF","benched":0,"injured":0,"subbedout":0,"tagged":0,"tagger":0,"freesfor":"1","freesagainst":"1","round":"10","date":0,"trimmedLink":2951},{"playerID":"M.DAmbrosio-16","number":"16","name":"M.DAmbrosio","goals":"0","behinds":"0","kicks":"15","handballs":"13","marks":"3","tackles":"3","hitouts":"0","tog":"83","fantasy":"92","fantasyAvg":"65.50","team":1,"teamName":"Hawthorn","url":null,"teamScore":"12.7","teamScoreTotal":79,"time":"Q4 34:46","sub":0,"breakeven":"72","price":"522,000","position":"DEF/MID","benched":0,"injured":0,"subbedout":0,"tagged":0,"tagger":0,"freesfor":"0","freesagainst":"0","round":"10","date":0,"trimmedLink":2951},{"playerID":"J.Newcombe-3","number":"3","name":"J.Newcombe","goals":"0","behinds":"0","kicks":"15","handballs":"8","marks":"4","tackles":"5","hitouts":"0","tog":"80","fantasy":"88","fantasyAvg":"81.80","team":1,"teamName":"Hawthorn","url":null,"teamScore":"12.7","teamScoreTotal":79,"time":"Q4 34:46","sub":0,"breakeven":"63","price":"743,000","position":"MID","benched":0,"injured":0,"subbedout":0,"tagged":0,"tagger":0,"freesfor":"1","freesagainst":"2","round":"10","date":0,"trimmedLink":2951},{"playerID":"C.MacDonald-31","number":"31","name":"C.MacDonald","goals":"0","behinds":"1","kicks":"6","handballs":"8","marks":"2","tackles":"8","hitouts":"0","tog":"83","fantasy":"72","fantasyAvg":"67.70","team":1,"teamName":"Hawthorn","url":null,"teamScore":"12.7","teamScoreTotal":79,"time":"Q4 34:46","sub":0,"breakeven":"76","price":"589,000","position":"FWD","benched":0,"injured":0,"subbedout":0,"tagged":0,"tagger":0,"freesfor":"2","freesagainst":"1","round":"10","date":0,"trimmedLink":2951},{"playerID":"C.Nash-11","number":"11","name":"C.Nash","goals":"0","behinds":"0","kicks":"8","handballs":"9","marks":"1","tackles":"7","hitouts":"0","tog":"74","fantasy":"71","fantasyAvg":"79.10","team":1,"teamName":"Hawthorn","url":null,"teamScore":"12.7","teamScoreTotal":79,"time":"Q4 34:46","sub":0,"breakeven":"84","price":"706,000","position":"MID","benched":0,"injured":0,"subbedout":0,"tagged":0,"tagger":1,"freesfor":"1","freesagainst":"1","round":"10","date":0,"trimmedLink":2951},{"playerID":"D.Moore-13","number":"13","name":"D.Moore","goals":"0","behinds":"1","kicks":"10","handballs":"6","marks":"1","tackles":"6","hitouts":"0","tog":"92","fantasy":"62","fantasyAvg":"83.60","team":1,"teamName":"Hawthorn","url":null,"teamScore":"12.7","teamScoreTotal":79,"time":"Q4 34:46","sub":0,"breakeven":"76","price":"765,000","position":"FWD","benched":0,"injured":0,"subbedout":0,"tagged":0,"tagger":0,"freesfor":"1","freesagainst":"3","round":"10","date":0,"trimmedLink":2951},{"playerID":"C.Mackenzie-28","number":"28","name":"C.Mackenzie","goals":"2","behinds":"0","kicks":"7","handballs":"5","marks":"0","tackles":"4","hitouts":"0","tog":"71","fantasy":"61","fantasyAvg":"54.70","team":1,"teamName":"Hawthorn","url":null,"teamScore":"12.7","teamScoreTotal":79,"time":"Q4 34:46","sub":0,"breakeven":"56","price":"467,000","position":"FWD/MID","benched":0,"injured":0,"subbedout":0,"tagged":0,"tagger":0,"freesfor":"2","freesagainst":"0","round":"10","date":0,"trimmedLink":2951},{"playerID":"J.Ginnivan-33","number":"33","name":"J.Ginnivan","goals":"1","behinds":"0","kicks":"9","handballs":"6","marks":"4","tackles":"1","hitouts":"0","tog":"78","fantasy":"58","fantasyAvg":"67.70","team":1,"teamName":"Hawthorn","url":null,"teamScore":"12.7","teamScoreTotal":79,"time":"Q4 34:46","sub":0,"breakeven":"57","price":"572,000","position":"FWD","benched":0,"injured":0,"subbedout":0,"tagged":0,"tagger":0,"freesfor":"0","freesagainst":"1","round":"10","date":0,"trimmedLink":2951},{"playerID":"C.Dear-35","number":"35","name":"C.Dear","goals":"1","behinds":"1","kicks":"5","handballs":"4","marks":"2","tackles":"5","hitouts":"0","tog":"83","fantasy":"56","fantasyAvg":"43.50","team":1,"teamName":"Hawthorn","url":null,"teamScore":"12.7","teamScoreTotal":79,"time":"Q4 34:46","sub":0,"breakeven":"14","price":"250,000","position":"FWD","benched":0,"injured":0,"subbedout":0,"tagged":0,"tagger":0,"freesfor":"3","freesagainst":"1","round":"10","date":0,"trimmedLink":2951},{"playerID":"J.Worpel-5","number":"5","name":"J.Worpel","goals":"0","behinds":"0","kicks":"7","handballs":"12","marks":"1","tackles":"2","hitouts":"0","tog":"76","fantasy":"53","fantasyAvg":"78.70","team":1,"teamName":"Hawthorn","url":null,"teamScore":"12.7","teamScoreTotal":79,"time":"Q4 34:46","sub":0,"breakeven":"94","price":"656,000","position":"MID","benched":0,"injured":0,"subbedout":0,"tagged":0,"tagger":0,"freesfor":"0","freesagainst":"1","round":"10","date":0,"trimmedLink":2951},{"playerID":"M.Chol-18","number":"18","name":"M.Chol","goals":"2","behinds":"1","kicks":"5","handballs":"4","marks":"1","tackles":"3","hitouts":"1","tog":"78","fantasy":"53","fantasyAvg":"58.40","team":1,"teamName":"Hawthorn","url":null,"teamScore":"12.7","teamScoreTotal":79,"time":"Q4 34:46","sub":0,"breakeven":"56","price":"496,000","position":"FWD","benched":0,"injured":0,"subbedout":0,"tagged":0,"tagger":0,"freesfor":"1","freesagainst":"0","round":"10","date":0,"trimmedLink":2951},{"playerID":"N.Watson-34","number":"34","name":"N.Watson","goals":"0","behinds":"1","kicks":"6","handballs":"5","marks":"3","tackles":"2","hitouts":"0","tog":"64","fantasy":"46","fantasyAvg":"47.00","team":1,"teamName":"Hawthorn","url":null,"teamScore":"12.7","teamScoreTotal":79,"time":"Q4 34:46","sub":0,"breakeven":"34","price":"370,000","position":"MID/FWD","benched":0,"injured":0,"subbedout":0,"tagged":0,"tagger":0,"freesfor":"0","freesagainst":"0","round":"10","date":0,"trimmedLink":2951},{"playerID":"J.Serong-29","number":"29","name":"J.Serong","goals":"0","behinds":"0","kicks":"2","handballs":"5","marks":"2","tackles":"6","hitouts":"0","tog":"78","fantasy":"46","fantasyAvg":"34.30","team":1,"teamName":"Hawthorn","url":null,"teamScore":"12.7","teamScoreTotal":79,"time":"Q4 34:46","sub":0,"breakeven":"34","price":"304,000","position":"DEF","benched":0,"injured":0,"subbedout":0,"tagged":0,"tagger":0,"freesfor":"0","freesagainst":"0","round":"10","date":0,"trimmedLink":2951},{"playerID":"J.Impey-4","number":"4","name":"J.Impey","goals":"0","behinds":"1","kicks":"9","handballs":"3","marks":"0","tackles":"2","hitouts":"0","tog":"80","fantasy":"42","fantasyAvg":"82.90","team":1,"teamName":"Hawthorn","url":null,"teamScore":"12.7","teamScoreTotal":79,"time":"Q4 34:46","sub":0,"breakeven":"65","price":"724,000","position":"DEF","benched":0,"injured":0,"subbedout":0,"tagged":0,"tagger":0,"freesfor":"0","freesagainst":"0","round":"10","date":0,"trimmedLink":2951},{"playerID":"E.Phillips-37","number":"37","name":"E.Phillips","goals":"0","behinds":"0","kicks":"6","handballs":"4","marks":"3","tackles":"1","hitouts":"0","tog":"87","fantasy":"39","fantasyAvg":"0.00","team":1,"teamName":"Hawthorn","url":null,"teamScore":"12.7","teamScoreTotal":79,"time":"Q4 34:46","sub":0,"breakeven":"25","price":"200,000","position":"DEF","benched":0,"injured":0,"subbedout":0,"tagged":0,"tagger":0,"freesfor":"0","freesagainst":"0","round":"10","date":0,"trimmedLink":2951},{"playerID":"S.Frost-8","number":"8","name":"S.Frost","goals":"0","behinds":"0","kicks":"6","handballs":"4","marks":"2","tackles":"2","hitouts":"0","tog":"100","fantasy":"34","fantasyAvg":"46.60","team":1,"teamName":"Hawthorn","url":null,"teamScore":"12.7","teamScoreTotal":79,"time":"Q4 34:46","sub":0,"breakeven":"49","price":"394,000","position":"DEF","benched":0,"injured":0,"subbedout":0,"tagged":0,"tagger":0,"freesfor":"0","freesagainst":"2","round":"10","date":0,"trimmedLink":2951},{"playerID":"J.Weddle-23","number":"23","name":"J.Weddle","goals":"0","behinds":"0","kicks":"6","handballs":"2","marks":"2","tackles":"2","hitouts":"0","tog":"89","fantasy":"33","fantasyAvg":"61.60","team":1,"teamName":"Hawthorn","url":null,"teamScore":"12.7","teamScoreTotal":79,"time":"Q4 34:46","sub":0,"breakeven":"71","price":"517,000","position":"DEF","benched":0,"injured":0,"subbedout":0,"tagged":0,"tagger":0,"freesfor":"0","freesagainst":"1","round":"10","date":0,"trimmedLink":2951},{"playerID":"C.Jiath-9","number":"9","name":"C.Jiath","goals":"0","behinds":"0","kicks":"5","handballs":"3","marks":"2","tackles":"1","hitouts":"0","tog":"58","fantasy":"31","fantasyAvg":"0.00","team":1,"teamName":"Hawthorn","url":null,"teamScore":"12.7","teamScoreTotal":79,"time":"Q4 34:46","sub":0,"breakeven":"70","price":"564,000","position":"DEF","benched":0,"injured":0,"subbedout":1,"tagged":0,"tagger":0,"freesfor":"0","freesagainst":"0","round":"10","date":0,"trimmedLink":2951},{"playerID":"S.Mitchell-40","number":"40","name":"S.Mitchell","goals":"0","behinds":"0","kicks":"3","handballs":"3","marks":"2","tackles":"3","hitouts":"0","tog":"76","fantasy":"30","fantasyAvg":"38.20","team":1,"teamName":"Hawthorn","url":null,"teamScore":"12.7","teamScoreTotal":79,"time":"Q4 34:46","sub":0,"breakeven":"62","price":"412,000","position":"DEF","benched":0,"injured":0,"subbedout":0,"tagged":0,"tagger":0,"freesfor":"0","freesagainst":"1","round":"10","date":0,"trimmedLink":2951},{"playerID":"L.Breust-22","number":"22","name":"L.Breust","goals":"0","behinds":"0","kicks":"2","handballs":"4","marks":"0","tackles":"2","hitouts":"0","tog":"27","fantasy":"16","fantasyAvg":"41.00","team":1,"teamName":"Hawthorn","url":null,"teamScore":"12.7","teamScoreTotal":79,"time":"Q4 34:46","sub":1,"breakeven":"87","price":"455,000","position":"FWD","benched":0,"injured":0,"subbedout":0,"tagged":0,"tagger":0,"freesfor":"0","freesagainst":"2","round":"10","date":0,"trimmedLink":2951}]}